BookerPdfTool/__init__.py
BookerPdfTool/__main__.py
BookerPdfTool/img2jb2pdf.py
BookerPdfTool/pdf_tool.py
BookerPdfTool/toggle_bw.py
BookerPdfTool/util.py
BookerPdfTool/zip_tool.py
BookerPdfTool/assets/7z.dll
BookerPdfTool/assets/7z.exe
BookerPdfTool/assets/PwdDic.txt
BookerPdfTool/assets/__init__.py
BookerPdfTool/assets/jbig2enc
BookerPdfTool/assets/jbig2enc.dll
BookerPdfTool/assets/jbig2enc.exe
BookerPdfTool/assets/unrar.exe
BookerPdfTool-2023.7.22.0.dist-info/LICENSE
BookerPdfTool-2023.7.22.0.dist-info/METADATA
BookerPdfTool-2023.7.22.0.dist-info/WHEEL
BookerPdfTool-2023.7.22.0.dist-info/entry_points.txt
BookerPdfTool-2023.7.22.0.dist-info/top_level.txt
BookerPdfTool-2023.7.22.0.dist-info/RECORD
