Metadata-Version: 2.1
Name: BookerPdfTool
Version: 2023.7.22.0
Summary: iBooker/ApacheCN 知识库抓取工具
Home-page: https://github.com/apachecn/BookerPdfTool
Author: wizardforcel
Author-email: wizard.z@qq.com
Keywords: wiki,知识库,document,文档,crawler,爬虫
Classifier: Development Status :: 4 - Beta
Classifier: Environment :: Console
Classifier: Intended Audience :: Developers
Classifier: Intended Audience :: End Users/Desktop
Classifier: License :: Other/Proprietary License
Classifier: Natural Language :: Chinese (Simplified)
Classifier: Natural Language :: English
Classifier: Operating System :: OS Independent
Classifier: Programming Language :: Python :: 3
Classifier: Programming Language :: Python :: 3 :: Only
Classifier: Programming Language :: Python :: 3.6
Classifier: Programming Language :: Python :: 3.7
Classifier: Topic :: Internet :: WWW/HTTP
Classifier: Topic :: Text Processing :: Markup :: HTML
Classifier: Topic :: Software Development :: Documentation
Classifier: Topic :: Software Development :: Localization
Classifier: Topic :: Utilities
Requires-Python: >=3.6
License-File: LICENSE
Requires-Dist: requests
Requires-Dist: pyquery
Requires-Dist: imgyaso
Requires-Dist: PyMuPdf
Requires-Dist: img2pdf
Requires-Dist: rarfile
Requires-Dist: numpy
Requires-Dist: opencv-python
Requires-Dist: img2jb2pdf
